{"LeagueName": "Ultraliga 2024 Spring", "Stage": "Week 5", "Team1Short": "WOLF", "Team2Short": "Forsaken (Polish Team)", "Team1Logo": "https://static.wikia.nocookie.net/lolesports_gamepedia_en/images/4/43/Iron_Wolveslogo_square.png/revision/latest?cb=20210907133250", "Team2Logo": "https://static.wikia.nocookie.net/lolesports_gamepedia_en/images/4/42/Forsaken_%28Polish_Team%29logo_square.png/revision/latest?cb=20220111195322", "Team1Ban": "Kalista, Rumble, Milio, Vi, Jarvan IV", "Ban1Img": ["http://ddragon.leagueoflegends.com/cdn/14.3.1/img/champion/Kalista.png", "http://ddragon.leagueoflegends.com/cdn/14.3.1/img/champion/Rumble.png", "http://ddragon.leagueoflegends.com/cdn/14.3.1/img/champion/Milio.png", "http://ddragon.leagueoflegends.com/cdn/14.3.1/img/champion/Vi.png", "http://ddragon.leagueoflegends.com/cdn/14.3.1/img/champion/JarvanIV.png"], "Ban2Img": ["http://ddragon.leagueoflegends.com/cdn/14.3.1/img/champion/Zac.png", "http://ddragon.leagueoflegends.com/cdn/14.3.1/img/champion/Karma.png", "http://ddragon.leagueoflegends.com/cdn/14.3.1/img/champion/Ashe.png", "http://ddragon.leagueoflegends.com/cdn/14.3.1/img/champion/Belveth.png", "http://ddragon.leagueoflegends.com/cdn/14.3.1/img/champion/LeeSin.png"], "Team2Ban": "Zac, Karma, Ashe, Bel'Veth, Lee Sin", "Team1Data": [[{"Player": "HeSSZero", "Champion": "K'Sante", "ChampionImg": "http://ddragon.leagueoflegends.com/cdn/14.3.1/img/champion/KSante.png", "Role": "Top", "Spells": "Ghost,Teleport", "KeystoneRune": "Grasp of the Undying", "SecondaryTree": "Inspiration", "Kills": "3", "Deaths": "2", "Assists": "5", "CS": "275", "Damage": "12,356"}], [{"Player": "kylin", "Champion": "Kindred", "ChampionImg": "http://ddragon.leagueoflegends.com/cdn/14.3.1/img/champion/Kindred.png", "Role": "Jungle", "Spells": "Flash,Smite", "KeystoneRune": "Conqueror", "SecondaryTree": "Inspiration", "Kills": "2", "Deaths": "6", "Assists": "5", "CS": "230", "Damage": "9,304"}], [{"Player": "0din", "Champion": "Hwei", "ChampionImg": "http://ddragon.leagueoflegends.com/cdn/14.3.1/img/champion/Hwei.png", "Role": "Mid", "Spells": "Flash,Teleport", "KeystoneRune": "Arcane Comet", "SecondaryTree": "Inspiration", "Kills": "2", "Deaths": "7", "Assists": "5", "CS": "240", "Damage": "20,833"}], [{"Player": "Ruf", "Champion": "Miss Fortune", "ChampionImg": "http://ddragon.leagueoflegends.com/cdn/14.3.1/img/champion/MissFortune.png", "Role": "Bot", "Spells": "Cleanse,Flash", "KeystoneRune": "First Strike", "SecondaryTree": "Sorcery", "Kills": "2", "Deaths": "6", "Assists": "8", "CS": "307", "Damage": "15,210"}], [{"Player": "Endz", "Champion": "Maokai", "ChampionImg": "http://ddragon.leagueoflegends.com/cdn/14.3.1/img/champion/Maokai.png", "Role": "Support", "Spells": "Flash,Ignite", "KeystoneRune": "Aftershock", "SecondaryTree": "Inspiration", "Kills": "4", "Deaths": "5", "Assists": "5", "CS": "50", "Damage": "10,681"}]], "Team2Data": [[{"Player": "Ariana", "Champion": "Twisted Fate", "ChampionImg": "http://ddragon.leagueoflegends.com/cdn/14.3.1/img/champion/TwistedFate.png", "Role": "Top", "Spells": "Flash,Ghost", "KeystoneRune": "Fleet Footwork", "SecondaryTree": "Sorcery", "Kills": "5", "Deaths": "6", "Assists": "3", "CS": "242", "Damage": "23,345"}], [{"Player": "belit", "Champion": "Rell", "ChampionImg": "http://ddragon.leagueoflegends.com/cdn/14.3.1/img/champion/Rell.png", "Role": "Jungle", "Spells": "Flash,Smite", "KeystoneRune": "Aftershock", "SecondaryTree": "Inspiration", "Kills": "3", "Deaths": "2", "Assists": "19", "CS": "169", "Damage": "8,188"}], [{"Player": "RAFBIN", "Champion": "Azir", "ChampionImg": "http://ddragon.leagueoflegends.com/cdn/14.3.1/img/champion/Azir.png", "Role": "Mid", "Spells": "Flash,Teleport", "KeystoneRune": "Fleet Footwork", "SecondaryTree": "Sorcery", "Kills": "6", "Deaths": "3", "Assists": "6", "CS": "320", "Damage": "23,831"}], [{"Player": "wittman", "Champion": "Varus", "ChampionImg": "http://ddragon.leagueoflegends.com/cdn/14.3.1/img/champion/Varus.png", "Role": "Bot", "Spells": "Flash,Cleanse", "KeystoneRune": "Hail of Blades", "SecondaryTree": "Inspiration", "Kills": "10", "Deaths": "1", "Assists": "11", "CS": "322", "Damage": "39,724"}], [{"Player": "Crisma", "Champion": "Bard", "ChampionImg": "http://ddragon.leagueoflegends.com/cdn/14.3.1/img/champion/Bard.png", "Role": "Support", "Spells": "Ignite,Flash", "KeystoneRune": "Guardian", "SecondaryTree": "Domination", "Kills": "2", "Deaths": "2", "Assists": "20", "CS": "29", "Damage": "10,063"}]], "Duration": "34:41", "Team1Kill": "13", "Team2Kill": "26", "Team1Gold": "58,840", "Team2Gold": "70,228", "Team1Dragon": "1", "Team2Dragon": "5", "Team1Baron": "0", "Team2Baron": "1", "Team1Tower": "2", "Team2Tower": "11", "Team1Score": "0", "Team2Score": "1"}