{"LeagueName": "LCK 2024 Spring", "Stage": "Week 3", "Team1Short": "NS", "Team2Short": "HLE", "Team1Logo": "https://static.wikia.nocookie.net/lolesports_gamepedia_en/images/b/b8/Nongshim_RedForcelogo_square.png/revision/latest?cb=20210325081928", "Team2Logo": "https://static.wikia.nocookie.net/lolesports_gamepedia_en/images/a/a6/Hanwha_Life_Esportslogo_square.png/revision/latest?cb=20211024145058", "Team1Ban": "Maokai, Vi, Rumble, Orianna, Yone", "Ban1Img": ["http://ddragon.leagueoflegends.com/cdn/14.2.1/img/champion/Maokai.png", "http://ddragon.leagueoflegends.com/cdn/14.2.1/img/champion/Vi.png", "http://ddragon.leagueoflegends.com/cdn/14.2.1/img/champion/Rumble.png", "http://ddragon.leagueoflegends.com/cdn/14.2.1/img/champion/Orianna.png", "http://ddragon.leagueoflegends.com/cdn/14.2.1/img/champion/Yone.png"], "Ban2Img": ["http://ddragon.leagueoflegends.com/cdn/14.2.1/img/champion/KSante.png", "http://ddragon.leagueoflegends.com/cdn/14.2.1/img/champion/Senna.png", "http://ddragon.leagueoflegends.com/cdn/14.2.1/img/champion/Azir.png", "http://ddragon.leagueoflegends.com/cdn/14.2.1/img/champion/Trundle.png", "http://ddragon.leagueoflegends.com/cdn/14.2.1/img/champion/Poppy.png"], "Team2Ban": "K'Sante, Senna, Azir, Trundle, Poppy", "Team1Data": [[{"Player": "DnDn", "Champion": "Jax", "ChampionImg": "http://ddragon.leagueoflegends.com/cdn/14.2.1/img/champion/Jax.png", "Role": "Top", "Spells": "Teleport,Flash", "KeystoneRune": "Grasp of the Undying", "SecondaryTree": "Inspiration", "Kills": "0", "Deaths": "2", "Assists": "0", "CS": "258", "Damage": "10,413"}], [{"Player": "Sylvie", "Champion": "Rell", "ChampionImg": "http://ddragon.leagueoflegends.com/cdn/14.2.1/img/champion/Rell.png", "Role": "Jungle", "Spells": "Smite,Flash", "KeystoneRune": "Aftershock", "SecondaryTree": "Inspiration", "Kills": "3", "Deaths": "2", "Assists": "1", "CS": "133", "Damage": "5,607"}], [{"Player": "Callme", "Champion": "Corki", "ChampionImg": "http://ddragon.leagueoflegends.com/cdn/14.2.1/img/champion/Corki.png", "Role": "Mid", "Spells": "Flash,Teleport", "KeystoneRune": "First Strike", "SecondaryTree": "Domination", "Kills": "0", "Deaths": "4", "Assists": "2", "CS": "220", "Damage": "17,548"}], [{"Player": "Jiwoo", "Champion": "Lucian", "ChampionImg": "http://ddragon.leagueoflegends.com/cdn/14.2.1/img/champion/Lucian.png", "Role": "Bot", "Spells": "Flash,Cleanse", "KeystoneRune": "First Strike", "SecondaryTree": "Sorcery", "Kills": "1", "Deaths": "3", "Assists": "1", "CS": "232", "Damage": "16,881"}], [{"Player": "Peter", "Champion": "Nami", "ChampionImg": "http://ddragon.leagueoflegends.com/cdn/14.2.1/img/champion/Nami.png", "Role": "Support", "Spells": "Flash,Heal", "KeystoneRune": "Summon Aery", "SecondaryTree": "Inspiration", "Kills": "0", "Deaths": "1", "Assists": "2", "CS": "58", "Damage": "6,004"}]], "Team2Data": [[{"Player": "Doran", "Champion": "Udyr", "ChampionImg": "http://ddragon.leagueoflegends.com/cdn/14.2.1/img/champion/Udyr.png", "Role": "Top", "Spells": "Teleport,Ghost", "KeystoneRune": "Grasp of the Undying", "SecondaryTree": "Inspiration", "Kills": "8", "Deaths": "1", "Assists": "2", "CS": "238", "Damage": "21,036"}], [{"Player": "Peanut", "Champion": "Sejuani", "ChampionImg": "http://ddragon.leagueoflegends.com/cdn/14.2.1/img/champion/Sejuani.png", "Role": "Jungle", "Spells": "Flash,Smite", "KeystoneRune": "Aftershock", "SecondaryTree": "Inspiration", "Kills": "1", "Deaths": "0", "Assists": "6", "CS": "177", "Damage": "5,388"}], [{"Player": "Zeka", "Champion": "Tristana", "ChampionImg": "http://ddragon.leagueoflegends.com/cdn/14.2.1/img/champion/Tristana.png", "Role": "Mid", "Spells": "Teleport,Flash", "KeystoneRune": "Fleet Footwork", "SecondaryTree": "Resolve", "Kills": "2", "Deaths": "1", "Assists": "4", "CS": "287", "Damage": "17,477"}], [{"Player": "Viper", "Champion": "Aphelios", "ChampionImg": "http://ddragon.leagueoflegends.com/cdn/14.2.1/img/champion/Aphelios.png", "Role": "Bot", "Spells": "Ghost,Flash", "KeystoneRune": "Fleet Footwork", "SecondaryTree": "Resolve", "Kills": "1", "Deaths": "2", "Assists": "5", "CS": "261", "Damage": "19,199"}], [{"Player": "Delight", "Champion": "Milio", "ChampionImg": "http://ddragon.leagueoflegends.com/cdn/14.2.1/img/champion/Milio.png", "Role": "Support", "Spells": "Heal,Flash", "KeystoneRune": "Summon Aery", "SecondaryTree": "Inspiration", "Kills": "0", "Deaths": "0", "Assists": "7", "CS": "54", "Damage": "3,165"}]], "Duration": "27:17", "Team1Kill": "4", "Team2Kill": "12", "Team1Gold": "42,339", "Team2Gold": "53,915", "Team1Dragon": "0", "Team2Dragon": "3", "Team1Baron": "0", "Team2Baron": "1", "Team1Tower": "0", "Team2Tower": "8", "Team1Score": "0", "Team2Score": "1"}