{"LeagueName": "EM 2024 Spring Main Event", "Stage": "Day 1", "Team1Short": "EINS", "Team2Short": "OAE", "Team1Logo": "https://static.wikia.nocookie.net/lolesports_gamepedia_en/images/f/f6/Eintracht_Spandaulogo_square.png/revision/latest?cb=20211114183152", "Team2Logo": "https://static.wikia.nocookie.net/lolesports_gamepedia_en/images/a/a5/Orbit_Anonymo_Esportslogo_square.png/revision/latest?cb=20230308163017", "Team1Ban": "Kalista, Maokai, Ziggs, Nautilus, Rell", "Ban1Img": ["http://ddragon.leagueoflegends.com/cdn/14.8.1/img/champion/Kalista.png", "http://ddragon.leagueoflegends.com/cdn/14.8.1/img/champion/Maokai.png", "http://ddragon.leagueoflegends.com/cdn/14.8.1/img/champion/Ziggs.png", "http://ddragon.leagueoflegends.com/cdn/14.8.1/img/champion/Nautilus.png", "http://ddragon.leagueoflegends.com/cdn/14.8.1/img/champion/Rell.png"], "Ban2Img": ["http://ddragon.leagueoflegends.com/cdn/14.8.1/img/champion/Rumble.png", "http://ddragon.leagueoflegends.com/cdn/14.8.1/img/champion/Orianna.png", "http://ddragon.leagueoflegends.com/cdn/14.8.1/img/champion/Taliyah.png", "http://ddragon.leagueoflegends.com/cdn/14.8.1/img/champion/Poppy.png", "http://ddragon.leagueoflegends.com/cdn/14.8.1/img/champion/Lulu.png"], "Team2Ban": "Rumble, Orianna, Taliyah, Poppy, Lulu", "Team1Data": [[{"Player": "Vertigo", "Champion": "Sion", "ChampionImg": "http://ddragon.leagueoflegends.com/cdn/14.8.1/img/champion/Sion.png", "Role": "Top", "Spells": "Teleport,Flash", "KeystoneRune": "Unsealed Spellbook", "SecondaryTree": "Resolve", "Kills": "1", "Deaths": "1", "Assists": "6", "CS": "166", "Damage": "8,950"}], [{"Player": "Zanzarah", "Champion": "Rek'Sai", "ChampionImg": "http://ddragon.leagueoflegends.com/cdn/14.8.1/img/champion/RekSai.png", "Role": "Jungle", "Spells": "Flash,Smite", "KeystoneRune": "Conqueror", "SecondaryTree": "Inspiration", "Kills": "3", "Deaths": "0", "Assists": "4", "CS": "133", "Damage": "4,017"}], [{"Player": "PowerOfEvil", "Champion": "Azir", "ChampionImg": "http://ddragon.leagueoflegends.com/cdn/14.8.1/img/champion/Azir.png", "Role": "Mid", "Spells": "Flash,Teleport", "KeystoneRune": "Hail of Blades", "SecondaryTree": "Inspiration", "Kills": "4", "Deaths": "0", "Assists": "5", "CS": "244", "Damage": "15,799"}], [{"Player": "Fun K3y", "Champion": "Jinx", "ChampionImg": "http://ddragon.leagueoflegends.com/cdn/14.8.1/img/champion/Jinx.png", "Role": "Bot", "Spells": "Flash,Cleanse", "KeystoneRune": "Lethal Tempo", "SecondaryTree": "Sorcery", "Kills": "2", "Deaths": "0", "Assists": "5", "CS": "213", "Damage": "11,535"}], [{"Player": "Lilipp", "Champion": "Rakan", "ChampionImg": "http://ddragon.leagueoflegends.com/cdn/14.8.1/img/champion/Rakan.png", "Role": "Support", "Spells": "Flash,Ignite", "KeystoneRune": "Guardian", "SecondaryTree": "Domination", "Kills": "0", "Deaths": "0", "Assists": "8", "CS": "28", "Damage": "4,092"}]], "Team2Data": [[{"Player": "pr1me", "Champion": "Jax", "ChampionImg": "http://ddragon.leagueoflegends.com/cdn/14.8.1/img/champion/Jax.png", "Role": "Top", "Spells": "Flash,Teleport", "KeystoneRune": "Lethal Tempo", "SecondaryTree": "Inspiration", "Kills": "0", "Deaths": "2", "Assists": "0", "CS": "158", "Damage": "2,395"}], [{"Player": "Afroboi", "Champion": "Vi", "ChampionImg": "http://ddragon.leagueoflegends.com/cdn/14.8.1/img/champion/Vi.png", "Role": "Jungle", "Spells": "Flash,Smite", "KeystoneRune": "Conqueror", "SecondaryTree": "Inspiration", "Kills": "1", "Deaths": "3", "Assists": "0", "CS": "124", "Damage": "3,175"}], [{"Player": "Roison", "Champion": "Aurelion Sol", "ChampionImg": "http://ddragon.leagueoflegends.com/cdn/14.8.1/img/champion/AurelionSol.png", "Role": "Mid", "Spells": "Flash,Teleport", "KeystoneRune": "Arcane Comet", "SecondaryTree": "Inspiration", "Kills": "0", "Deaths": "2", "Assists": "0", "CS": "193", "Damage": "9,032"}], [{"Player": "Neramin", "Champion": "Kai'Sa", "ChampionImg": "http://ddragon.leagueoflegends.com/cdn/14.8.1/img/champion/Kaisa.png", "Role": "Bot", "Spells": "Flash,Heal", "KeystoneRune": "Lethal Tempo", "SecondaryTree": "Inspiration", "Kills": "0", "Deaths": "1", "Assists": "1", "CS": "203", "Damage": "8,562"}], [{"Player": "Czypsy", "Champion": "Leona", "ChampionImg": "http://ddragon.leagueoflegends.com/cdn/14.8.1/img/champion/Leona.png", "Role": "Support", "Spells": "Flash,Ignite", "KeystoneRune": "Aftershock", "SecondaryTree": "Inspiration", "Kills": "0", "Deaths": "2", "Assists": "1", "CS": "32", "Damage": "2,114"}]], "Duration": "22:58", "Team1Kill": "10", "Team2Kill": "1", "Team1Gold": "46,471", "Team2Gold": "32,242", "Team1Dragon": "1", "Team2Dragon": "2", "Team1Baron": "1", "Team2Baron": "0", "Team1Tower": "9", "Team2Tower": "0", "Team1Score": "1", "Team2Score": "0"}