{"LeagueName": "Legend Cup 2024", "Stage": "Groups Day 3", "Team1Short": "Omnipotence", "Team2Short": "Zeal Temperature", "Team1Logo": "https://static.wikia.nocookie.net/lolesports_gamepedia_en/images/9/97/Omnipotencelogo_square.png/revision/latest?cb=20240507152942", "Team2Logo": "https://static.wikia.nocookie.net/lolesports_gamepedia_en/images/9/98/Zeal_Temperaturelogo_square.png/revision/latest?cb=20240507152945", "Team1Ban": "Ahri, Orianna, Ashe, Braum, Vi", "Ban1Img": ["http://ddragon.leagueoflegends.com/cdn/14.10.1/img/champion/Ahri.png", "http://ddragon.leagueoflegends.com/cdn/14.10.1/img/champion/Orianna.png", "http://ddragon.leagueoflegends.com/cdn/14.10.1/img/champion/Ashe.png", "http://ddragon.leagueoflegends.com/cdn/14.10.1/img/champion/Braum.png", "http://ddragon.leagueoflegends.com/cdn/14.10.1/img/champion/Vi.png"], "Ban2Img": ["http://ddragon.leagueoflegends.com/cdn/14.10.1/img/champion/Tristana.png", "http://ddragon.leagueoflegends.com/cdn/14.10.1/img/champion/Rumble.png", "http://ddragon.leagueoflegends.com/cdn/14.10.1/img/champion/Azir.png", "http://ddragon.leagueoflegends.com/cdn/14.10.1/img/champion/Gnar.png", "http://ddragon.leagueoflegends.com/cdn/14.10.1/img/champion/Sejuani.png"], "Team2Ban": "Tristana, Rumble, Azir, Gnar, Sejuani", "Team1Data": [[{"Player": "TheShy", "Champion": "Camille", "ChampionImg": "http://ddragon.leagueoflegends.com/cdn/14.10.1/img/champion/Camille.png", "Role": "Top", "Spells": "Flash,Teleport", "KeystoneRune": "Grasp of the Undying", "SecondaryTree": "Inspiration", "Kills": "0", "Deaths": "3", "Assists": "3", "CS": "209", "Damage": "17,329"}], [{"Player": "Ning", "Champion": "Xin Zhao", "ChampionImg": "http://ddragon.leagueoflegends.com/cdn/14.10.1/img/champion/XinZhao.png", "Role": "Jungle", "Spells": "Smite,Flash", "KeystoneRune": "Lethal Tempo", "SecondaryTree": "Inspiration", "Kills": "2", "Deaths": "1", "Assists": "4", "CS": "190", "Damage": "5,735"}], [{"Player": "xiaocaobao", "Champion": "Corki", "ChampionImg": "http://ddragon.leagueoflegends.com/cdn/14.10.1/img/champion/Corki.png", "Role": "Mid", "Spells": "Flash,Teleport", "KeystoneRune": "First Strike", "SecondaryTree": "Domination", "Kills": "5", "Deaths": "0", "Assists": "5", "CS": "259", "Damage": "22,531"}], [{"Player": "wx", "Champion": "Kalista", "ChampionImg": "http://ddragon.leagueoflegends.com/cdn/14.10.1/img/champion/Kalista.png", "Role": "Bot", "Spells": "Heal,Flash", "KeystoneRune": "Hail of Blades", "SecondaryTree": "Inspiration", "Kills": "2", "Deaths": "2", "Assists": "6", "CS": "199", "Damage": "4,556"}], [{"Player": "Fireloli", "Champion": "Renata Glasc", "ChampionImg": "http://ddragon.leagueoflegends.com/cdn/14.10.1/img/champion/Renata.png", "Role": "Support", "Spells": "Flash,Ignite", "KeystoneRune": "Guardian", "SecondaryTree": "Domination", "Kills": "3", "Deaths": "2", "Assists": "7", "CS": "33", "Damage": "4,868"}]], "Team2Data": [[{"Player": "957", "Champion": "Poppy", "ChampionImg": "http://ddragon.leagueoflegends.com/cdn/14.10.1/img/champion/Poppy.png", "Role": "Top", "Spells": "Flash,Teleport", "KeystoneRune": "Grasp of the Undying", "SecondaryTree": "Inspiration", "Kills": "0", "Deaths": "1", "Assists": "4", "CS": "174", "Damage": "11,514"}], [{"Player": "XLB", "Champion": "Rengar", "ChampionImg": "http://ddragon.leagueoflegends.com/cdn/14.10.1/img/champion/Rengar.png", "Role": "Jungle", "Spells": "Smite,Flash", "KeystoneRune": "First Strike", "SecondaryTree": "Domination", "Kills": "3", "Deaths": "2", "Assists": "1", "CS": "171", "Damage": "4,359"}], [{"Player": "Zz1tai", "Champion": "Taliyah", "ChampionImg": "http://ddragon.leagueoflegends.com/cdn/14.10.1/img/champion/Taliyah.png", "Role": "Mid", "Spells": "Flash,Teleport", "KeystoneRune": "Phase Rush", "SecondaryTree": "Inspiration", "Kills": "3", "Deaths": "4", "Assists": "4", "CS": "204", "Damage": "12,827"}], [{"Player": "Vas1lii", "Champion": "Varus", "ChampionImg": "http://ddragon.leagueoflegends.com/cdn/14.10.1/img/champion/Varus.png", "Role": "Bot", "Spells": "Ghost,Flash", "KeystoneRune": "Lethal Tempo", "SecondaryTree": "Inspiration", "Kills": "0", "Deaths": "3", "Assists": "4", "CS": "233", "Damage": "8,862"}], [{"Player": "yuyanjia", "Champion": "Neeko", "ChampionImg": "http://ddragon.leagueoflegends.com/cdn/14.10.1/img/champion/Neeko.png", "Role": "Support", "Spells": "Heal,Flash", "KeystoneRune": "Arcane Comet", "SecondaryTree": "Inspiration", "Kills": "2", "Deaths": "2", "Assists": "2", "CS": "40", "Damage": "3,989"}]], "Duration": "24:05", "Team1Kill": "12", "Team2Kill": "8", "Team1Gold": "49,434", "Team2Gold": "40,404", "Team1Dragon": "2", "Team2Dragon": "1", "Team1Baron": "1", "Team2Baron": "0", "Team1Tower": "8", "Team2Tower": "2", "Team1Score": "1", "Team2Score": "0"}