{"LeagueName": "LCK 2024 Spring Playoffs", "Stage": "Round 1", "Team1Short": "KT", "Team2Short": "DK", "Team1Logo": "https://static.wikia.nocookie.net/lolesports_gamepedia_en/images/f/f8/KT_Rolsterlogo_square.png/revision/latest?cb=20210605165230", "Team2Logo": "https://static.wikia.nocookie.net/lolesports_gamepedia_en/images/7/73/Dplus_KIAlogo_square.png/revision/latest?cb=20230512050104", "Team1Ban": "Rell, Maokai, Zeri, Xin Zhao, Rek'Sai", "Ban1Img": ["http://ddragon.leagueoflegends.com/cdn/14.6.1/img/champion/Rell.png", "http://ddragon.leagueoflegends.com/cdn/14.6.1/img/champion/Maokai.png", "http://ddragon.leagueoflegends.com/cdn/14.6.1/img/champion/Zeri.png", "http://ddragon.leagueoflegends.com/cdn/14.6.1/img/champion/XinZhao.png", "http://ddragon.leagueoflegends.com/cdn/14.6.1/img/champion/RekSai.png"], "Ban2Img": ["http://ddragon.leagueoflegends.com/cdn/14.6.1/img/champion/Senna.png", "http://ddragon.leagueoflegends.com/cdn/14.6.1/img/champion/Varus.png", "http://ddragon.leagueoflegends.com/cdn/14.6.1/img/champion/Kalista.png", "http://ddragon.leagueoflegends.com/cdn/14.6.1/img/champion/Taliyah.png", "http://ddragon.leagueoflegends.com/cdn/14.6.1/img/champion/Gnar.png"], "Team2Ban": "Senna, Varus, Kalista, Taliyah, Gnar", "Team1Data": [[{"Player": "PerfecT", "Champion": "Renekton", "ChampionImg": "http://ddragon.leagueoflegends.com/cdn/14.6.1/img/champion/Renekton.png", "Role": "Top", "Spells": "Flash,Teleport", "KeystoneRune": "Conqueror", "SecondaryTree": "Resolve", "Kills": "11", "Deaths": "1", "Assists": "7", "CS": "325", "Damage": "27,910"}], [{"Player": "Pyosik", "Champion": "Vi", "ChampionImg": "http://ddragon.leagueoflegends.com/cdn/14.6.1/img/champion/Vi.png", "Role": "Jungle", "Spells": "Smite,Flash", "KeystoneRune": "Conqueror", "SecondaryTree": "Inspiration", "Kills": "4", "Deaths": "4", "Assists": "9", "CS": "217", "Damage": "11,153"}], [{"Player": "Bdd", "Champion": "Veigar", "ChampionImg": "http://ddragon.leagueoflegends.com/cdn/14.6.1/img/champion/Veigar.png", "Role": "Mid", "Spells": "Flash,Teleport", "KeystoneRune": "Summon Aery", "SecondaryTree": "Inspiration", "Kills": "5", "Deaths": "2", "Assists": "8", "CS": "371", "Damage": "21,859"}], [{"Player": "Deft", "Champion": "Ashe", "ChampionImg": "http://ddragon.leagueoflegends.com/cdn/14.6.1/img/champion/Ashe.png", "Role": "Bot", "Spells": "Flash,Heal", "KeystoneRune": "Hail of Blades", "SecondaryTree": "Resolve", "Kills": "2", "Deaths": "1", "Assists": "13", "CS": "311", "Damage": "29,504"}], [{"Player": "BeryL", "Champion": "Rumble", "ChampionImg": "http://ddragon.leagueoflegends.com/cdn/14.6.1/img/champion/Rumble.png", "Role": "Support", "Spells": "Ignite,Flash", "KeystoneRune": "Arcane Comet", "SecondaryTree": "Inspiration", "Kills": "5", "Deaths": "4", "Assists": "9", "CS": "38", "Damage": "21,732"}]], "Team2Data": [[{"Player": "Kingen", "Champion": "K'Sante", "ChampionImg": "http://ddragon.leagueoflegends.com/cdn/14.6.1/img/champion/KSante.png", "Role": "Top", "Spells": "Teleport,Ghost", "KeystoneRune": "Grasp of the Undying", "SecondaryTree": "Inspiration", "Kills": "0", "Deaths": "8", "Assists": "6", "CS": "271", "Damage": "14,554"}], [{"Player": "Lucid", "Champion": "Nocturne", "ChampionImg": "http://ddragon.leagueoflegends.com/cdn/14.6.1/img/champion/Nocturne.png", "Role": "Jungle", "Spells": "Smite,Flash", "KeystoneRune": "Lethal Tempo", "SecondaryTree": "Domination", "Kills": "2", "Deaths": "5", "Assists": "6", "CS": "224", "Damage": "11,716"}], [{"Player": "ShowMaker", "Champion": "Azir", "ChampionImg": "http://ddragon.leagueoflegends.com/cdn/14.6.1/img/champion/Azir.png", "Role": "Mid", "Spells": "Teleport,Flash", "KeystoneRune": "Grasp of the Undying", "SecondaryTree": "Precision", "Kills": "3", "Deaths": "3", "Assists": "2", "CS": "380", "Damage": "25,490"}], [{"Player": "Aiming", "Champion": "Lucian", "ChampionImg": "http://ddragon.leagueoflegends.com/cdn/14.6.1/img/champion/Lucian.png", "Role": "Bot", "Spells": "Cleanse,Flash", "KeystoneRune": "First Strike", "SecondaryTree": "Sorcery", "Kills": "6", "Deaths": "5", "Assists": "4", "CS": "337", "Damage": "29,882"}], [{"Player": "Kellin", "Champion": "Nami", "ChampionImg": "http://ddragon.leagueoflegends.com/cdn/14.6.1/img/champion/Nami.png", "Role": "Support", "Spells": "Heal,Flash", "KeystoneRune": "Summon Aery", "SecondaryTree": "Inspiration", "Kills": "1", "Deaths": "6", "Assists": "8", "CS": "26", "Damage": "7,817"}]], "Duration": "39:30", "Team1Kill": "27", "Team2Kill": "12", "Team1Gold": "76,667", "Team2Gold": "71,615", "Team1Dragon": "5", "Team2Dragon": "1", "Team1Baron": "1", "Team2Baron": "1", "Team1Tower": "8", "Team2Tower": "8", "Team1Score": "2", "Team2Score": "1"}