{"LeagueName": "LRS 2024 Season", "Stage": "Week 6", "Team1Short": "UBK", "Team2Short": "FG", "Team1Logo": "https://static.wikia.nocookie.net/lolesports_gamepedia_en/images/b/b7/Undead_Gaminglogo_square.png/revision/latest?cb=20210829032530", "Team2Logo": "https://static.wikia.nocookie.net/lolesports_gamepedia_en/images/a/ae/Furious_Gaminglogo_square.png/revision/latest?cb=20221028045023", "Team1Ban": "Nautilus, Rumble, Lucian, Ornn, K'Sante", "Ban1Img": ["http://ddragon.leagueoflegends.com/cdn/14.10.1/img/champion/Nautilus.png", "http://ddragon.leagueoflegends.com/cdn/14.10.1/img/champion/Rumble.png", "http://ddragon.leagueoflegends.com/cdn/14.10.1/img/champion/Lucian.png", "http://ddragon.leagueoflegends.com/cdn/14.10.1/img/champion/Ornn.png", "http://ddragon.leagueoflegends.com/cdn/14.10.1/img/champion/KSante.png"], "Ban2Img": ["http://ddragon.leagueoflegends.com/cdn/14.10.1/img/champion/Corki.png", "http://ddragon.leagueoflegends.com/cdn/14.10.1/img/champion/Azir.png", "http://ddragon.leagueoflegends.com/cdn/14.10.1/img/champion/Tristana.png", "http://ddragon.leagueoflegends.com/cdn/14.10.1/img/champion/Camille.png", "http://ddragon.leagueoflegends.com/cdn/14.10.1/img/champion/Poppy.png"], "Team2Ban": "Corki, Azir, Tristana, Camille, Poppy", "Team1Data": [[{"Player": "Acce", "Champion": "Jayce", "ChampionImg": "http://ddragon.leagueoflegends.com/cdn/14.10.1/img/champion/Jayce.png", "Role": "Top", "Spells": "Flash,Teleport", "KeystoneRune": "Conqueror", "SecondaryTree": "Inspiration", "Kills": "2", "Deaths": "5", "Assists": "2", "CS": "364", "Damage": "21,899"}], [{"Player": "KinGi", "Champion": "Brand", "ChampionImg": "http://ddragon.leagueoflegends.com/cdn/14.10.1/img/champion/Brand.png", "Role": "Jungle", "Spells": "Flash,Smite", "KeystoneRune": "Electrocute", "SecondaryTree": "Inspiration", "Kills": "5", "Deaths": "7", "Assists": "6", "CS": "245", "Damage": "22,672"}], [{"Player": "Kiefer", "Champion": "Ahri", "ChampionImg": "http://ddragon.leagueoflegends.com/cdn/14.10.1/img/champion/Ahri.png", "Role": "Mid", "Spells": "Flash,Teleport", "KeystoneRune": "Electrocute", "SecondaryTree": "Inspiration", "Kills": "2", "Deaths": "3", "Assists": "6", "CS": "348", "Damage": "22,107"}], [{"Player": "Naitz", "Champion": "Caitlyn", "ChampionImg": "http://ddragon.leagueoflegends.com/cdn/14.10.1/img/champion/Caitlyn.png", "Role": "Bot", "Spells": "Flash,Cleanse", "KeystoneRune": "Fleet Footwork", "SecondaryTree": "Sorcery", "Kills": "3", "Deaths": "1", "Assists": "4", "CS": "390", "Damage": "23,300"}], [{"Player": "Gastruks", "Champion": "Alistar", "ChampionImg": "http://ddragon.leagueoflegends.com/cdn/14.10.1/img/champion/Alistar.png", "Role": "Support", "Spells": "Ignite,Flash", "KeystoneRune": "Aftershock", "SecondaryTree": "Inspiration", "Kills": "0", "Deaths": "5", "Assists": "6", "CS": "32", "Damage": "2,875"}]], "Team2Data": [[{"Player": "Sunblast", "Champion": "Zac", "ChampionImg": "http://ddragon.leagueoflegends.com/cdn/14.10.1/img/champion/Zac.png", "Role": "Top", "Spells": "Flash,Teleport", "KeystoneRune": "Grasp of the Undying", "SecondaryTree": "Inspiration", "Kills": "3", "Deaths": "1", "Assists": "4", "CS": "286", "Damage": "7,660"}], [{"Player": "Pancake", "Champion": "Kha'Zix", "ChampionImg": "http://ddragon.leagueoflegends.com/cdn/14.10.1/img/champion/Khazix.png", "Role": "Jungle", "Spells": "Flash,Smite", "KeystoneRune": "First Strike", "SecondaryTree": "Domination", "Kills": "4", "Deaths": "4", "Assists": "8", "CS": "240", "Damage": "17,963"}], [{"Player": "Chordy", "Champion": "Hwei", "ChampionImg": "http://ddragon.leagueoflegends.com/cdn/14.10.1/img/champion/Hwei.png", "Role": "Mid", "Spells": "Teleport,Flash", "KeystoneRune": "First Strike", "SecondaryTree": "Sorcery", "Kills": "8", "Deaths": "1", "Assists": "10", "CS": "326", "Damage": "40,658"}], [{"Player": "ianshaka", "Champion": "Jhin", "ChampionImg": "http://ddragon.leagueoflegends.com/cdn/14.10.1/img/champion/Jhin.png", "Role": "Bot", "Spells": "Flash,Heal", "KeystoneRune": "Fleet Footwork", "SecondaryTree": "Inspiration", "Kills": "4", "Deaths": "2", "Assists": "8", "CS": "381", "Damage": "16,815"}], [{"Player": "Bardito", "Champion": "Rell", "ChampionImg": "http://ddragon.leagueoflegends.com/cdn/14.10.1/img/champion/Rell.png", "Role": "Support", "Spells": "Ignite,Flash", "KeystoneRune": "Aftershock", "SecondaryTree": "Inspiration", "Kills": "2", "Deaths": "4", "Assists": "14", "CS": "40", "Damage": "5,417"}]], "Duration": "38:26", "Team1Kill": "12", "Team2Kill": "21", "Team1Gold": "67,699", "Team2Gold": "76,660", "Team1Dragon": "3", "Team2Dragon": "2", "Team1Baron": "0", "Team2Baron": "2", "Team1Tower": "3", "Team2Tower": "10", "Team1Score": "0", "Team2Score": "1"}