{"LeagueName": "PRM 2nd Division 2024 Spring", "Stage": "Week 6", "Team1Short": "A41G", "Team2Short": "ROSS", "Team1Logo": "https://static.wikia.nocookie.net/lolesports_gamepedia_en/images/9/9a/All_for_One_Gaming_Blacklogo_square.png/revision/latest?cb=20210325124008", "Team2Logo": "https://static.wikia.nocookie.net/lolesports_gamepedia_en/images/8/8e/ROSSMANN_Centaurslogo_square.png/revision/latest?cb=20240106014202", "Team1Ban": "Karma, Twisted Fate, Varus, Fiora, Gwen", "Ban1Img": ["http://ddragon.leagueoflegends.com/cdn/14.4.1/img/champion/Karma.png", "http://ddragon.leagueoflegends.com/cdn/14.4.1/img/champion/TwistedFate.png", "http://ddragon.leagueoflegends.com/cdn/14.4.1/img/champion/Varus.png", "http://ddragon.leagueoflegends.com/cdn/14.4.1/img/champion/Fiora.png", "http://ddragon.leagueoflegends.com/cdn/14.4.1/img/champion/Gwen.png"], "Ban2Img": ["http://ddragon.leagueoflegends.com/cdn/14.4.1/img/champion/KSante.png", "http://ddragon.leagueoflegends.com/cdn/14.4.1/img/champion/Nocturne.png", "http://ddragon.leagueoflegends.com/cdn/14.4.1/img/champion/Maokai.png", "http://ddragon.leagueoflegends.com/cdn/14.4.1/img/champion/Poppy.png", "http://ddragon.leagueoflegends.com/cdn/14.4.1/img/champion/Vi.png"], "Team2Ban": "K'Sante, Nocturne, Maokai, Poppy, Vi", "Team1Data": [[{"Player": "OBELISK", "Champion": "Sion", "ChampionImg": "http://ddragon.leagueoflegends.com/cdn/14.4.1/img/champion/Sion.png", "Role": "Top", "Spells": "Teleport,Flash", "KeystoneRune": "Grasp of the Undying", "SecondaryTree": "Inspiration", "Kills": "1", "Deaths": "3", "Assists": "9", "CS": "220", "Damage": "11,683"}], [{"Player": "DIBU", "Champion": "Lee Sin", "ChampionImg": "http://ddragon.leagueoflegends.com/cdn/14.4.1/img/champion/LeeSin.png", "Role": "Jungle", "Spells": "Flash,Smite", "KeystoneRune": "Conqueror", "SecondaryTree": "Inspiration", "Kills": "12", "Deaths": "2", "Assists": "11", "CS": "154", "Damage": "17,422"}], [{"Player": "H0NEST", "Champion": "Azir", "ChampionImg": "http://ddragon.leagueoflegends.com/cdn/14.4.1/img/champion/Azir.png", "Role": "Mid", "Spells": "Flash,Teleport", "KeystoneRune": "Grasp of the Undying", "SecondaryTree": "Precision", "Kills": "6", "Deaths": "1", "Assists": "9", "CS": "228", "Damage": "16,672"}], [{"Player": "Notiko", "Champion": "Smolder", "ChampionImg": "http://ddragon.leagueoflegends.com/cdn/14.4.1/img/champion/Smolder.png", "Role": "Bot", "Spells": "Flash,Heal", "KeystoneRune": "Fleet Footwork", "SecondaryTree": "Inspiration", "Kills": "8", "Deaths": "2", "Assists": "11", "CS": "250", "Damage": "28,194"}], [{"Player": "Ephekles", "Champion": "Nautilus", "ChampionImg": "http://ddragon.leagueoflegends.com/cdn/14.4.1/img/champion/Nautilus.png", "Role": "Support", "Spells": "Flash,Ignite", "KeystoneRune": "Aftershock", "SecondaryTree": "Inspiration", "Kills": "0", "Deaths": "0", "Assists": "22", "CS": "22", "Damage": "8,814"}]], "Team2Data": [[{"Player": "NiceGuyBen", "Champion": "Urgot", "ChampionImg": "http://ddragon.leagueoflegends.com/cdn/14.4.1/img/champion/Urgot.png", "Role": "Top", "Spells": "Flash,Teleport", "KeystoneRune": "Fleet Footwork", "SecondaryTree": "Resolve", "Kills": "1", "Deaths": "5", "Assists": "2", "CS": "276", "Damage": "17,669"}], [{"Player": "Xagog", "Champion": "Gragas", "ChampionImg": "http://ddragon.leagueoflegends.com/cdn/14.4.1/img/champion/Gragas.png", "Role": "Jungle", "Spells": "Smite,Flash", "KeystoneRune": "Electrocute", "SecondaryTree": "Inspiration", "Kills": "4", "Deaths": "6", "Assists": "4", "CS": "158", "Damage": "19,599"}], [{"Player": "goose", "Champion": "Yasuo", "ChampionImg": "http://ddragon.leagueoflegends.com/cdn/14.4.1/img/champion/Yasuo.png", "Role": "Mid", "Spells": "Teleport,Flash", "KeystoneRune": "Fleet Footwork", "SecondaryTree": "Resolve", "Kills": "2", "Deaths": "5", "Assists": "1", "CS": "247", "Damage": "9,771"}], [{"Player": "M4rth", "Champion": "Senna", "ChampionImg": "http://ddragon.leagueoflegends.com/cdn/14.4.1/img/champion/Senna.png", "Role": "Bot", "Spells": "Flash,Heal", "KeystoneRune": "Fleet Footwork", "SecondaryTree": "Resolve", "Kills": "1", "Deaths": "6", "Assists": "3", "CS": "175", "Damage": "14,113"}], [{"Player": "Wildenbruch", "Champion": "Tahm Kench", "ChampionImg": "http://ddragon.leagueoflegends.com/cdn/14.4.1/img/champion/TahmKench.png", "Role": "Support", "Spells": "Ignite,Flash", "KeystoneRune": "Grasp of the Undying", "SecondaryTree": "Precision", "Kills": "0", "Deaths": "5", "Assists": "2", "CS": "28", "Damage": "6,607"}]], "Duration": "28:20", "Team1Kill": "27", "Team2Kill": "8", "Team1Gold": "58,651", "Team2Gold": "49,541", "Team1Dragon": "2", "Team2Dragon": "1", "Team1Baron": "1", "Team2Baron": "0", "Team1Tower": "9", "Team2Tower": "3", "Team1Score": "1", "Team2Score": "0"}