{"LeagueName": "LCK 2024 Spring", "Stage": "Week 4", "Team1Short": "HLE", "Team2Short": "BRO", "Team1Logo": "https://static.wikia.nocookie.net/lolesports_gamepedia_en/images/a/a6/Hanwha_Life_Esportslogo_square.png/revision/latest?cb=20211024145058", "Team2Logo": "https://static.wikia.nocookie.net/lolesports_gamepedia_en/images/c/cf/BRIONlogo_square.png/revision/latest?cb=20230518062717", "Team1Ban": "Varus, Poppy, Karma, Tristana, Azir", "Ban1Img": ["http://ddragon.leagueoflegends.com/cdn/14.3.1/img/champion/Varus.png", "http://ddragon.leagueoflegends.com/cdn/14.3.1/img/champion/Poppy.png", "http://ddragon.leagueoflegends.com/cdn/14.3.1/img/champion/Karma.png", "http://ddragon.leagueoflegends.com/cdn/14.3.1/img/champion/Tristana.png", "http://ddragon.leagueoflegends.com/cdn/14.3.1/img/champion/Azir.png"], "Ban2Img": ["http://ddragon.leagueoflegends.com/cdn/14.3.1/img/champion/Corki.png", "http://ddragon.leagueoflegends.com/cdn/14.3.1/img/champion/Kalista.png", "http://ddragon.leagueoflegends.com/cdn/14.3.1/img/champion/Vi.png", "http://ddragon.leagueoflegends.com/cdn/14.3.1/img/champion/Udyr.png", "http://ddragon.leagueoflegends.com/cdn/14.3.1/img/champion/Gnar.png"], "Team2Ban": "Corki, Kalista, Vi, Udyr, Gnar", "Team1Data": [[{"Player": "Doran", "Champion": "Aatrox", "ChampionImg": "http://ddragon.leagueoflegends.com/cdn/14.3.1/img/champion/Aatrox.png", "Role": "Top", "Spells": "Teleport,Flash", "KeystoneRune": "Conqueror", "SecondaryTree": "Resolve", "Kills": "4", "Deaths": "2", "Assists": "6", "CS": "248", "Damage": "19,275"}], [{"Player": "Peanut", "Champion": "Sejuani", "ChampionImg": "http://ddragon.leagueoflegends.com/cdn/14.3.1/img/champion/Sejuani.png", "Role": "Jungle", "Spells": "Flash,Smite", "KeystoneRune": "Aftershock", "SecondaryTree": "Inspiration", "Kills": "2", "Deaths": "0", "Assists": "10", "CS": "167", "Damage": "8,048"}], [{"Player": "Zeka", "Champion": "Orianna", "ChampionImg": "http://ddragon.leagueoflegends.com/cdn/14.3.1/img/champion/Orianna.png", "Role": "Mid", "Spells": "Teleport,Flash", "KeystoneRune": "Summon Aery", "SecondaryTree": "Inspiration", "Kills": "4", "Deaths": "2", "Assists": "7", "CS": "246", "Damage": "19,867"}], [{"Player": "Viper", "Champion": "Senna", "ChampionImg": "http://ddragon.leagueoflegends.com/cdn/14.3.1/img/champion/Senna.png", "Role": "Bot", "Spells": "Heal,Flash", "KeystoneRune": "Fleet Footwork", "SecondaryTree": "Inspiration", "Kills": "3", "Deaths": "0", "Assists": "8", "CS": "67", "Damage": "19,038"}], [{"Player": "Delight", "Champion": "Nautilus", "ChampionImg": "http://ddragon.leagueoflegends.com/cdn/14.3.1/img/champion/Nautilus.png", "Role": "Support", "Spells": "Teleport,Flash", "KeystoneRune": "Aftershock", "SecondaryTree": "Inspiration", "Kills": "0", "Deaths": "2", "Assists": "10", "CS": "176", "Damage": "6,173"}]], "Team2Data": [[{"Player": "Morgan", "Champion": "K'Sante", "ChampionImg": "http://ddragon.leagueoflegends.com/cdn/14.3.1/img/champion/KSante.png", "Role": "Top", "Spells": "Teleport,Ghost", "KeystoneRune": "Grasp of the Undying", "SecondaryTree": "Inspiration", "Kills": "2", "Deaths": "4", "Assists": "2", "CS": "200", "Damage": "6,569"}], [{"Player": "GIDEON", "Champion": "Lee Sin", "ChampionImg": "http://ddragon.leagueoflegends.com/cdn/14.3.1/img/champion/LeeSin.png", "Role": "Jungle", "Spells": "Smite,Flash", "KeystoneRune": "Conqueror", "SecondaryTree": "Inspiration", "Kills": "0", "Deaths": "4", "Assists": "3", "CS": "155", "Damage": "5,162"}], [{"Player": "Karis", "Champion": "Akali", "ChampionImg": "http://ddragon.leagueoflegends.com/cdn/14.3.1/img/champion/Akali.png", "Role": "Mid", "Spells": "Flash,Teleport", "KeystoneRune": "Fleet Footwork", "SecondaryTree": "Resolve", "Kills": "1", "Deaths": "3", "Assists": "2", "CS": "224", "Damage": "10,217"}], [{"Player": "Samver", "Champion": "Lucian", "ChampionImg": "http://ddragon.leagueoflegends.com/cdn/14.3.1/img/champion/Lucian.png", "Role": "Bot", "Spells": "Ignite,Flash", "KeystoneRune": "Press the Attack", "SecondaryTree": "Inspiration", "Kills": "3", "Deaths": "1", "Assists": "3", "CS": "250", "Damage": "20,861"}], [{"Player": "Pollu", "Champion": "Milio", "ChampionImg": "http://ddragon.leagueoflegends.com/cdn/14.3.1/img/champion/Milio.png", "Role": "Support", "Spells": "Flash,Heal", "KeystoneRune": "Summon Aery", "SecondaryTree": "Inspiration", "Kills": "0", "Deaths": "1", "Assists": "5", "CS": "27", "Damage": "3,483"}]], "Duration": "26:46", "Team1Kill": "13", "Team2Kill": "6", "Team1Gold": "53,338", "Team2Gold": "42,937", "Team1Dragon": "2", "Team2Dragon": "1", "Team1Baron": "1", "Team2Baron": "0", "Team1Tower": "10", "Team2Tower": "1", "Team1Score": "1", "Team2Score": "0"}