{"LeagueName": "Hitpoint 2nd Div Challengers 2024 Spring", "Stage": "Week 3", "Team1Short": "STU", "Team2Short": "FLY5", "Team1Logo": "https://static.wikia.nocookie.net/lolesports_gamepedia_en/images/5/52/Esport_STUBAlogo_square.png/revision/latest?cb=20210103082557", "Team2Logo": "https://static.wikia.nocookie.net/lolesports_gamepedia_en/images/a/a5/Fly5logo_square.png/revision/latest?cb=20220612125900", "Team1Ban": "Fiora, Gwen, Varus, Vayne, None", "Ban1Img": ["http://ddragon.leagueoflegends.com/cdn/14.3.1/img/champion/Fiora.png", "http://ddragon.leagueoflegends.com/cdn/14.3.1/img/champion/Gwen.png", "http://ddragon.leagueoflegends.com/cdn/14.3.1/img/champion/Varus.png", "http://ddragon.leagueoflegends.com/cdn/14.3.1/img/champion/Vayne.png", "http://ddragon.leagueoflegends.com/cdn/14.3.1/img/champion/None.png"], "Ban2Img": ["http://ddragon.leagueoflegends.com/cdn/14.3.1/img/champion/Ivern.png", "http://ddragon.leagueoflegends.com/cdn/14.3.1/img/champion/Corki.png", "http://ddragon.leagueoflegends.com/cdn/14.3.1/img/champion/Karma.png", "http://ddragon.leagueoflegends.com/cdn/14.3.1/img/champion/KSante.png", "http://ddragon.leagueoflegends.com/cdn/14.3.1/img/champion/Ornn.png"], "Team2Ban": "Ivern, Corki, Karma, K'Sante, Ornn", "Team1Data": [[{"Player": "Scarpy", "Champion": "Malphite", "ChampionImg": "http://ddragon.leagueoflegends.com/cdn/14.3.1/img/champion/Malphite.png", "Role": "Top", "Spells": "Teleport,Flash", "KeystoneRune": "Arcane Comet", "SecondaryTree": "Resolve", "Kills": "0", "Deaths": "3", "Assists": "9", "CS": "240", "Damage": "20,481"}], [{"Player": "Goksi", "Champion": "Xin Zhao", "ChampionImg": "http://ddragon.leagueoflegends.com/cdn/14.3.1/img/champion/XinZhao.png", "Role": "Jungle", "Spells": "Flash,Smite", "KeystoneRune": "Conqueror", "SecondaryTree": "Inspiration", "Kills": "5", "Deaths": "3", "Assists": "4", "CS": "215", "Damage": "13,925"}], [{"Player": "Samyaza", "Champion": "Neeko", "ChampionImg": "http://ddragon.leagueoflegends.com/cdn/14.3.1/img/champion/Neeko.png", "Role": "Mid", "Spells": "Teleport,Flash", "KeystoneRune": "Arcane Comet", "SecondaryTree": "Inspiration", "Kills": "2", "Deaths": "6", "Assists": "4", "CS": "293", "Damage": "19,650"}], [{"Player": "Dzejno", "Champion": "Ezreal", "ChampionImg": "http://ddragon.leagueoflegends.com/cdn/14.3.1/img/champion/Ezreal.png", "Role": "Bot", "Spells": "Flash,Heal", "KeystoneRune": "Conqueror", "SecondaryTree": "Inspiration", "Kills": "5", "Deaths": "4", "Assists": "5", "CS": "322", "Damage": "32,611"}], [{"Player": "Siriass", "Champion": "Hwei", "ChampionImg": "http://ddragon.leagueoflegends.com/cdn/14.3.1/img/champion/Hwei.png", "Role": "Support", "Spells": "Flash,Barrier", "KeystoneRune": "Arcane Comet", "SecondaryTree": "Inspiration", "Kills": "2", "Deaths": "7", "Assists": "8", "CS": "59", "Damage": "16,192"}]], "Team2Data": [[{"Player": "r0bbed", "Champion": "Aatrox", "ChampionImg": "http://ddragon.leagueoflegends.com/cdn/14.3.1/img/champion/Aatrox.png", "Role": "Top", "Spells": "Flash,Teleport", "KeystoneRune": "Conqueror", "SecondaryTree": "Resolve", "Kills": "8", "Deaths": "1", "Assists": "5", "CS": "276", "Damage": "23,709"}], [{"Player": "0ri", "Champion": "Maokai", "ChampionImg": "http://ddragon.leagueoflegends.com/cdn/14.3.1/img/champion/Maokai.png", "Role": "Jungle", "Spells": "Flash,Smite", "KeystoneRune": "Aftershock", "SecondaryTree": "Domination", "Kills": "4", "Deaths": "3", "Assists": "9", "CS": "150", "Damage": "15,711"}], [{"Player": "Sined", "Champion": "Azir", "ChampionImg": "http://ddragon.leagueoflegends.com/cdn/14.3.1/img/champion/Azir.png", "Role": "Mid", "Spells": "Teleport,Flash", "KeystoneRune": "Press the Attack", "SecondaryTree": "Sorcery", "Kills": "6", "Deaths": "1", "Assists": "4", "CS": "324", "Damage": "30,140"}], [{"Player": "Dejw", "Champion": "Draven", "ChampionImg": "http://ddragon.leagueoflegends.com/cdn/14.3.1/img/champion/Draven.png", "Role": "Bot", "Spells": "Flash,Heal", "KeystoneRune": "Hail of Blades", "SecondaryTree": "Precision", "Kills": "5", "Deaths": "4", "Assists": "7", "CS": "241", "Damage": "16,055"}], [{"Player": "Marco", "Champion": "Ashe", "ChampionImg": "http://ddragon.leagueoflegends.com/cdn/14.3.1/img/champion/Ashe.png", "Role": "Support", "Spells": "Barrier,Flash", "KeystoneRune": "Hail of Blades", "SecondaryTree": "Resolve", "Kills": "0", "Deaths": "5", "Assists": "17", "CS": "51", "Damage": "17,227"}]], "Duration": "33:58", "Team1Kill": "14", "Team2Kill": "23", "Team1Gold": "61,222", "Team2Gold": "69,527", "Team1Dragon": "3", "Team2Dragon": "2", "Team1Baron": "0", "Team2Baron": "2", "Team1Tower": "2", "Team2Tower": "11", "Team1Score": "0", "Team2Score": "1"}