{"LeagueName": "LIT 2024 Spring", "Stage": "Week 2", "Team1Short": "AXL", "Team2Short": "ATE", "Team1Logo": "https://static.wikia.nocookie.net/lolesports_gamepedia_en/images/3/3a/Axolotllogo_square.png/revision/latest?cb=20211217030948", "Team2Logo": "https://static.wikia.nocookie.net/lolesports_gamepedia_en/images/8/8e/Atleta_Esportlogo_square.png/revision/latest?cb=20210823144309", "Team1Ban": "Rumble, Poppy, Ashe, Maokai, Udyr", "Ban1Img": ["http://ddragon.leagueoflegends.com/cdn/14.2.1/img/champion/Rumble.png", "http://ddragon.leagueoflegends.com/cdn/14.2.1/img/champion/Poppy.png", "http://ddragon.leagueoflegends.com/cdn/14.2.1/img/champion/Ashe.png", "http://ddragon.leagueoflegends.com/cdn/14.2.1/img/champion/Maokai.png", "http://ddragon.leagueoflegends.com/cdn/14.2.1/img/champion/Udyr.png"], "Ban2Img": ["http://ddragon.leagueoflegends.com/cdn/14.2.1/img/champion/Galio.png", "http://ddragon.leagueoflegends.com/cdn/14.2.1/img/champion/Neeko.png", "http://ddragon.leagueoflegends.com/cdn/14.2.1/img/champion/Kalista.png", "http://ddragon.leagueoflegends.com/cdn/14.2.1/img/champion/Aatrox.png", "http://ddragon.leagueoflegends.com/cdn/14.2.1/img/champion/Nautilus.png"], "Team2Ban": "Galio, Neeko, Kalista, Aatrox, Nautilus", "Team1Data": [[{"Player": "Achille", "Champion": "K'Sante", "ChampionImg": "http://ddragon.leagueoflegends.com/cdn/14.2.1/img/champion/KSante.png", "Role": "Top", "Spells": "Ghost,Teleport", "KeystoneRune": "Grasp of the Undying", "SecondaryTree": "Inspiration", "Kills": "0", "Deaths": "6", "Assists": "2", "CS": "180", "Damage": "7,048"}], [{"Player": "Bananiasty", "Champion": "Vi", "ChampionImg": "http://ddragon.leagueoflegends.com/cdn/14.2.1/img/champion/Vi.png", "Role": "Jungle", "Spells": "Smite,Flash", "KeystoneRune": "Conqueror", "SecondaryTree": "Inspiration", "Kills": "0", "Deaths": "5", "Assists": "4", "CS": "131", "Damage": "6,325"}], [{"Player": "Sadaz", "Champion": "Akali", "ChampionImg": "http://ddragon.leagueoflegends.com/cdn/14.2.1/img/champion/Akali.png", "Role": "Mid", "Spells": "Flash,Teleport", "KeystoneRune": "Fleet Footwork", "SecondaryTree": "Resolve", "Kills": "3", "Deaths": "2", "Assists": "2", "CS": "234", "Damage": "12,203"}], [{"Player": "CHECKFIDER", "Champion": "Varus", "ChampionImg": "http://ddragon.leagueoflegends.com/cdn/14.2.1/img/champion/Varus.png", "Role": "Bot", "Spells": "Flash,Ghost", "KeystoneRune": "Lethal Tempo", "SecondaryTree": "Inspiration", "Kills": "2", "Deaths": "4", "Assists": "0", "CS": "224", "Damage": "15,000"}], [{"Player": "Joao", "Champion": "Rell", "ChampionImg": "http://ddragon.leagueoflegends.com/cdn/14.2.1/img/champion/Rell.png", "Role": "Support", "Spells": "Flash,Ignite", "KeystoneRune": "Glacial Augment", "SecondaryTree": "Resolve", "Kills": "1", "Deaths": "3", "Assists": "2", "CS": "34", "Damage": "2,706"}]], "Team2Data": [[{"Player": "Eyliph", "Champion": "Ornn", "ChampionImg": "http://ddragon.leagueoflegends.com/cdn/14.2.1/img/champion/Ornn.png", "Role": "Top", "Spells": "Teleport,Flash", "KeystoneRune": "Grasp of the Undying", "SecondaryTree": "Inspiration", "Kills": "7", "Deaths": "0", "Assists": "9", "CS": "228", "Damage": "17,549"}], [{"Player": "Kikis", "Champion": "Xin Zhao", "ChampionImg": "http://ddragon.leagueoflegends.com/cdn/14.2.1/img/champion/XinZhao.png", "Role": "Jungle", "Spells": "Flash,Smite", "KeystoneRune": "Lethal Tempo", "SecondaryTree": "Inspiration", "Kills": "4", "Deaths": "2", "Assists": "9", "CS": "210", "Damage": "14,207"}], [{"Player": "Sebekx", "Champion": "Corki", "ChampionImg": "http://ddragon.leagueoflegends.com/cdn/14.2.1/img/champion/Corki.png", "Role": "Mid", "Spells": "Teleport,Flash", "KeystoneRune": "First Strike", "SecondaryTree": "Resolve", "Kills": "6", "Deaths": "2", "Assists": "11", "CS": "233", "Damage": "30,333"}], [{"Player": "PiOk", "Champion": "Lucian", "ChampionImg": "http://ddragon.leagueoflegends.com/cdn/14.2.1/img/champion/Lucian.png", "Role": "Bot", "Spells": "Flash,Cleanse", "KeystoneRune": "Press the Attack", "SecondaryTree": "Inspiration", "Kills": "3", "Deaths": "1", "Assists": "6", "CS": "261", "Damage": "9,908"}], [{"Player": "TasteLess", "Champion": "Nami", "ChampionImg": "http://ddragon.leagueoflegends.com/cdn/14.2.1/img/champion/Nami.png", "Role": "Support", "Spells": "Flash,Heal", "KeystoneRune": "Summon Aery", "SecondaryTree": "Inspiration", "Kills": "0", "Deaths": "1", "Assists": "19", "CS": "16", "Damage": "7,499"}]], "Duration": "26:56", "Team1Kill": "6", "Team2Kill": "20", "Team1Gold": "43,037", "Team2Gold": "56,492", "Team1Dragon": "2", "Team2Dragon": "2", "Team1Baron": "0", "Team2Baron": "1", "Team1Tower": "3", "Team2Tower": "10", "Team1Score": "0", "Team2Score": "1"}