{"LeagueName": "LDL 2024 Split 2", "Stage": "Week 5", "Team1Short": "IGY", "Team2Short": "FPB", "Team1Logo": "https://static.wikia.nocookie.net/lolesports_gamepedia_en/images/a/a5/Young_Glorylogo_square.png/revision/latest?cb=20210701124715", "Team2Logo": "https://static.wikia.nocookie.net/lolesports_gamepedia_en/images/6/69/FunPlus_Phoenix_Blazelogo_square.png/revision/latest?cb=20210107124629", "Team1Ban": "Lucian, Nautilus, Nidalee, Jax, Malphite", "Ban1Img": ["http://ddragon.leagueoflegends.com/cdn/14.10.1/img/champion/Lucian.png", "http://ddragon.leagueoflegends.com/cdn/14.10.1/img/champion/Nautilus.png", "http://ddragon.leagueoflegends.com/cdn/14.10.1/img/champion/Nidalee.png", "http://ddragon.leagueoflegends.com/cdn/14.10.1/img/champion/Jax.png", "http://ddragon.leagueoflegends.com/cdn/14.10.1/img/champion/Malphite.png"], "Ban2Img": ["http://ddragon.leagueoflegends.com/cdn/14.10.1/img/champion/Rumble.png", "http://ddragon.leagueoflegends.com/cdn/14.10.1/img/champion/Draven.png", "http://ddragon.leagueoflegends.com/cdn/14.10.1/img/champion/Ashe.png", "http://ddragon.leagueoflegends.com/cdn/14.10.1/img/champion/Gangplank.png", "http://ddragon.leagueoflegends.com/cdn/14.10.1/img/champion/Renekton.png"], "Team2Ban": "Rumble, Draven, Ashe, Gangplank, Renekton", "Team1Data": [[{"Player": "Wen", "Champion": "Twisted Fate", "ChampionImg": "http://ddragon.leagueoflegends.com/cdn/14.10.1/img/champion/TwistedFate.png", "Role": "Top", "Spells": "Ghost,Flash", "KeystoneRune": "Fleet Footwork", "SecondaryTree": "Sorcery", "Kills": "3", "Deaths": "4", "Assists": "3", "CS": "236", "Damage": "18,233"}], [{"Player": "Tyrion", "Champion": "Bel'Veth", "ChampionImg": "http://ddragon.leagueoflegends.com/cdn/14.10.1/img/champion/Belveth.png", "Role": "Jungle", "Spells": "Smite,Flash", "KeystoneRune": "Conqueror", "SecondaryTree": "Inspiration", "Kills": "2", "Deaths": "4", "Assists": "4", "CS": "187", "Damage": "4,412"}], [{"Player": "Mentality", "Champion": "Taliyah", "ChampionImg": "http://ddragon.leagueoflegends.com/cdn/14.10.1/img/champion/Taliyah.png", "Role": "Mid", "Spells": "Teleport,Flash", "KeystoneRune": "Phase Rush", "SecondaryTree": "Inspiration", "Kills": "2", "Deaths": "5", "Assists": "4", "CS": "238", "Damage": "13,414"}], [{"Player": "cute", "Champion": "Kalista", "ChampionImg": "http://ddragon.leagueoflegends.com/cdn/14.10.1/img/champion/Kalista.png", "Role": "Bot", "Spells": "Flash,Cleanse", "KeystoneRune": "Hail of Blades", "SecondaryTree": "Inspiration", "Kills": "4", "Deaths": "3", "Assists": "1", "CS": "263", "Damage": "13,154"}], [{"Player": "Jerry", "Champion": "Renata Glasc", "ChampionImg": "http://ddragon.leagueoflegends.com/cdn/14.10.1/img/champion/Renata.png", "Role": "Support", "Spells": "Ignite,Flash", "KeystoneRune": "Guardian", "SecondaryTree": "Domination", "Kills": "0", "Deaths": "0", "Assists": "10", "CS": "47", "Damage": "5,459"}]], "Team2Data": [[{"Player": "xiao7", "Champion": "Skarner", "ChampionImg": "http://ddragon.leagueoflegends.com/cdn/14.10.1/img/champion/Skarner.png", "Role": "Top", "Spells": "Flash,Teleport", "KeystoneRune": "Arcane Comet", "SecondaryTree": "Resolve", "Kills": "2", "Deaths": "3", "Assists": "9", "CS": "164", "Damage": "10,584"}], [{"Player": "sorrow", "Champion": "Karthus", "ChampionImg": "http://ddragon.leagueoflegends.com/cdn/14.10.1/img/champion/Karthus.png", "Role": "Jungle", "Spells": "Exhaust,Smite", "KeystoneRune": "Dark Harvest", "SecondaryTree": "Precision", "Kills": "6", "Deaths": "4", "Assists": "8", "CS": "235", "Damage": "26,565"}], [{"Player": "Yummy", "Champion": "Jayce", "ChampionImg": "http://ddragon.leagueoflegends.com/cdn/14.10.1/img/champion/Jayce.png", "Role": "Mid", "Spells": "Teleport,Flash", "KeystoneRune": "Phase Rush", "SecondaryTree": "Inspiration", "Kills": "4", "Deaths": "1", "Assists": "7", "CS": "301", "Damage": "25,222"}], [{"Player": "Xingye", "Champion": "Varus", "ChampionImg": "http://ddragon.leagueoflegends.com/cdn/14.10.1/img/champion/Varus.png", "Role": "Bot", "Spells": "Cleanse,Flash", "KeystoneRune": "Arcane Comet", "SecondaryTree": "Inspiration", "Kills": "4", "Deaths": "1", "Assists": "4", "CS": "255", "Damage": "20,366"}], [{"Player": "Lele", "Champion": "Neeko", "ChampionImg": "http://ddragon.leagueoflegends.com/cdn/14.10.1/img/champion/Neeko.png", "Role": "Support", "Spells": "Flash,Ignite", "KeystoneRune": "Arcane Comet", "SecondaryTree": "Inspiration", "Kills": "0", "Deaths": "2", "Assists": "10", "CS": "50", "Damage": "9,903"}]], "Duration": "31:00", "Team1Kill": "11", "Team2Kill": "16", "Team1Gold": "53,853", "Team2Gold": "60,006", "Team1Dragon": "1", "Team2Dragon": "3", "Team1Baron": "0", "Team2Baron": "1", "Team1Tower": "2", "Team2Tower": "10", "Team1Score": "0", "Team2Score": "2"}